rfrx/__init__.py
rfrx/protronik.py
rfrx/sbus.py
rfrx-2.1.2.dist-info/LICENSE
rfrx-2.1.2.dist-info/METADATA
rfrx-2.1.2.dist-info/WHEEL
rfrx-2.1.2.dist-info/entry_points.txt
rfrx-2.1.2.dist-info/RECORD
