Metadata-Version: 2.1
Name: rfrx
Version: 2.1.2
Summary: Receive RF frames from SBUS and Pro-Tronik PTR-6A v2
Home-page: https://github.com/nim65s/rfrx
License: BSD-2-Clause
Author: Guilhem Saurel
Author-email: guilhem.saurel@laas.fr
Requires-Python: >=3.7,<4.0
Classifier: License :: OSI Approved :: BSD License
Classifier: Programming Language :: Python :: 3
Classifier: Programming Language :: Python :: 3.7
Classifier: Programming Language :: Python :: 3.8
Classifier: Programming Language :: Python :: 3.9
Classifier: Programming Language :: Python :: 3.10
Classifier: Programming Language :: Python :: 3.11
Requires-Dist: pyserial (>=3.5,<4.0)
Project-URL: changelog, https://github.com/nim65s/rfrx/blob/main/CHANGELOG.md
